evo/data_converters/ubc/__init__.py
evo/data_converters/ubc/importer/__init__.py
evo/data_converters/ubc/importer/ubc_reader.py
evo/data_converters/ubc/importer/ubc_to_evo.py
evo/data_converters/ubc/importer/utils.py
evo_data_converters_ubc-0.1.4.dist-info/METADATA
evo_data_converters_ubc-0.1.4.dist-info/WHEEL
evo_data_converters_ubc-0.1.4.dist-info/licenses/LICENSE.md
evo_data_converters_ubc-0.1.4.dist-info/RECORD
