Metadata-Version: 2.4
Name: evo-data-converters-ubc
Version: 0.1.4
Summary: Python data converters for UBC to Evo geoscience objects
Project-URL: Source, https://github.com/SeequentEvo/evo-python-sdk
Project-URL: Tracker, https://github.com/SeequentEvo/evo-python-sdk/issues
Project-URL: Homepage, https://www.seequent.com/
Project-URL: Documentation, https://developer.seequent.com/
Author-email: Seequent <support@seequent.com>
License-File: LICENSE.md
Requires-Python: >=3.10
Requires-Dist: evo-data-converters-common>=0.3.1
